{"batchcomplete": "", "query": {"normalized": [{"to": "Georg Mehlis", "from": "Georg_Mehlis"}], "pages": {"1255644": {"extract": "Georg Mehlis (8 March 1878 – 13 November 1942) was a German neo-Kantian philosopher. Initially he was a philosopher of history in the style of Heinrich Rickert.\nHe edited (with Richard Kroner) Logos, Internationale Zeitschrift für Philosophie der Kultur, from 1910 (Logos was the title from 1912), with contributions by many leading German intellectual figures; which had an Italian stable-mate from 1914.\nHe turned in the 1920s to an interest in mysticism; and then wrote books on fascism. His ideas on aesthetics have been taken up by Suzanne Langer.\n\n\n== Works ==\nDie Geschichtsphilosophie Auguste Comtes (1909)\nEinführing in ein Systeme der Religionsphilosophie (1917)\nProbleme der Ethik (1918)\nÜber Formen der modernen Lyrik und Epik (Axel Lübbe). Eine kunstphilosophische Studie (1922)\nDie deutsche Romantik (1922)\nPlotin (1924)\nDie Mystik in der Fülle ihrer Erscheinungsformen in allen Zeiten und Kulturen (1927)\nDie Idee Mussolinis und der Sinn des Faschismus (1928)\nDer Staat Mussolinis (1929)\nPhilosophie der Gegenwart (1932)\nFreiheit und Faschismus (1934)", "ns": 0, "pageid": 1255644, "title": "Georg Mehlis"}}}, "limits": {"extracts": 20}, "warnings": {"extracts": {"*": "exlimit was too large for a whole article extracts request, lowered to 1"}, "main": {"*": "Unrecognized parameter: 'rvprop'"}}}