{"batchcomplete": "", "query": {"normalized": [{"to": "Lucius Annaeus Seneca", "from": "Lucius_Annaeus_Seneca"}], "pages": {"2622953": {"extract": "From a longer title: This is a redirect from a title that is a complete, more complete or longer version of the name of a person, organization, legislative act, etc. It leads to the title in accordance with the naming conventions for common names and can help writing and searches. However, do not replace these redirected links with a piped link unless the page is updated for another reason.", "ns": 0, "pageid": 2622953, "title": "Lucius Annaeus Seneca"}}}, "limits": {"extracts": 20}, "warnings": {"extracts": {"*": "exlimit was too large for a whole article extracts request, lowered to 1"}, "main": {"*": "Unrecognized parameter: 'rvprop'"}}}