{"batchcomplete": "", "query": {"normalized": [{"to": "Theodore Slaman", "from": "Theodore_Slaman"}], "pages": {"5693320": {"extract": "Theodore Allen Slaman (born April 17, 1954) is a professor of mathematics at the University of California, Berkeley who works in recursion theory.\nSlaman and W. Hugh Woodin formulated the Bi-interpretability Conjecture for the Turing degrees, which conjectures that the partial order of the Turing degrees is logically equivalent to second order arithmetic. They showed that the Bi-interpretability Conjecture is equivalent to there being no nontrivial automorphism of the Turing degrees. They also exhibited limits on the possible automorphisms of the Turing degrees by showing that any automorphism will be arithmetically definable.\n\n\n== References ==\nSlaman, Theodore A. (1991). \"Degree structures\". Proceedings of the International Congress of Mathematicians, Vol. I, II (Kyoto, 1990). pp. 303–316. MR 93b:03074. \n\n\n== External links ==\nhome page.\nTheodore Slaman at the Mathematics Genealogy Project", "ns": 0, "pageid": 5693320, "title": "Theodore Slaman"}}}, "limits": {"extracts": 20}, "warnings": {"extracts": {"*": "exlimit was too large for a whole article extracts request, lowered to 1"}, "main": {"*": "Unrecognized parameter: 'rvprop'"}}}